[
  {
    "state": "ALABAMA",
    "city": "Montgomery",
    "latitude": 32.377716,
    "longitude": -86.300568
  },
  {
    "state": "ALASKA",
    "city": "Juneau",
    "latitude": 58.301598,
    "longitude": -134.420212
  },
  {
    "state": "ARIZONA",
    "city": "Phoenix",
    "latitude": 33.448143,
    "longitude": -112.096962
  },
  {
    "state": "ARKANSAS",
    "city": "Little Rock",
    "latitude": 34.746613,
    "longitude": -92.288986
  },
  {
    "state": "CALIFORNIA",
    "city": "Sacramento",
    "latitude": 38.576668,
    "longitude": -121.493629
  },
  {
    "state": "COLORADO",
    "city": "Denver",
    "latitude": 39.739227,
    "longitude": -104.984856
  },
  {
    "state": "CONNECTICUT",
    "city": "Hartford",
    "latitude": 41.764046,
    "longitude": -72.682198
  },
  {
    "state": "DELAWARE",
    "city": "Dover",
    "latitude": 39.157307,
    "longitude": -75.519722
  },
  {
    "state": "HAWAII",
    "city": "Honolulu",
    "latitude": 21.307442,
    "longitude": -157.857376
  },
  {
    "state": "FLORIDA",
    "city": "Tallahassee",
    "latitude": 30.438118,
    "longitude": -84.281296
  },
  {
    "state": "GEORGIA",
    "city": "Atlanta",
    "latitude": 33.749027,
    "longitude": -84.388229
  },
  {
    "state": "IDAHO",
    "city": "Boise",
    "latitude": 43.617775,
    "longitude": -116.199722
  },
  {
    "state": "ILLINOIS",
    "city": "Springfield",
    "latitude": 39.798363,
    "longitude": -89.654961
  },
  {
    "state": "INDIANA",
    "city": "Indianapolis",
    "latitude": 39.768623,
    "longitude": -86.162643
  },
  {
    "state": "IOWA",
    "city": "Des Moines",
    "latitude": 41.591087,
    "longitude": -93.603729
  },
  {
    "state": "KANSAS",
    "city": "Topeka",
    "latitude": 39.048191,
    "longitude": -95.677956
  },
  {
    "state": "KENTUCKY",
    "city": "Frankfort",
    "latitude": 38.186722,
    "longitude": -84.875374
  },
  {
    "state": "LOUISIANA",
    "city": "Baton Rouge",
    "latitude": 30.457069,
    "longitude": -91.187393
  },
  {
    "state": "MAINE",
    "city": "Augusta",
    "latitude": 44.307167,
    "longitude": -69.781693
  },
  {
    "state": "MARYLAND",
    "city": "Annapolis",
    "latitude": 38.978764,
    "longitude": -76.490936
  },
  {
    "state": "MASSACHUSETTS",
    "city": "Boston",
    "latitude": 42.358162,
    "longitude": -71.063698
  },
  {
    "state": "MICHIGAN",
    "city": "Lansing",
    "latitude": 42.733635,
    "longitude": -84.555328
  },
  {
    "state": "MINNESOTA",
    "city": "St. Paul",
    "latitude": 44.955097,
    "longitude": -93.102211
  },
  {
    "state": "MISSISSIPPI",
    "city": "Jackson",
    "latitude": 32.303848,
    "longitude": -90.182106
  },
  {
    "state": "MISSOURI",
    "city": "Jefferson City",
    "latitude": 38.579201,
    "longitude": -92.172935
  },
  {
    "state": "MONTANA",
    "city": "Helena",
    "latitude": 46.585709,
    "longitude": -112.018417
  },
  {
    "state": "NEBRASKA",
    "city": "Lincoln",
    "latitude": 40.808075,
    "longitude": -96.699654
  },
  {
    "state": "NEVADA",
    "city": "Carson City",
    "latitude": 39.163914,
    "longitude": -119.766121
  },
  {
    "state": "NEW HAMPSHIRE",
    "city": "Concord",
    "latitude": 43.206898,
    "longitude": -71.537994
  },
  {
    "state": "NEW JERSEY",
    "city": "Trenton",
    "latitude": 40.220596,
    "longitude": -74.769913
  },
  {
    "state": "NEW MEXICO",
    "city": "Santa Fe",
    "latitude": 35.68224,
    "longitude": -105.939728
  },
  {
    "state": "NORTH CAROLINA",
    "city": "Raleigh",
    "latitude": 35.78043,
    "longitude": -78.639099
  },
  {
    "state": "NORTH DAKOTA",
    "city": "Bismarck",
    "latitude": 46.82085,
    "longitude": -100.783318
  },
  {
    "state": "NEW YORK",
    "city": "Albany",
    "latitude": 42.652843,
    "longitude": -73.757874
  },
  {
    "state": "OHIO",
    "city": "Columbus",
    "latitude": 39.961346,
    "longitude": -82.999069
  },
  {
    "state": "OKLAHOMA",
    "city": "Oklahoma City",
    "latitude": 35.492207,
    "longitude": -97.503342
  },
  {
    "state": "OREGON",
    "city": "Salem",
    "latitude": 44.938461,
    "longitude": -123.030403
  },
  {
    "state": "PENNSYLVANIA",
    "city": "Harrisburg",
    "latitude": 40.264378,
    "longitude": -76.883598
  },
  {
    "state": "RHODE ISLAND",
    "city": "Providence",
    "latitude": 41.830914,
    "longitude": -71.414963
  },
  {
    "state": "SOUTH CAROLINA",
    "city": "Columbia",
    "latitude": 34.000343,
    "longitude": -81.033211
  },
  {
    "state": "SOUTH DAKOTA",
    "city": "Pierre",
    "latitude": 44.367031,
    "longitude": -100.346405
  },
  {
    "state": "TENNESSEE",
    "city": "Nashville",
    "latitude": 36.16581,
    "longitude": -86.784241
  },
  {
    "state": "TEXAS",
    "city": "Austin",
    "latitude": 30.27467,
    "longitude": -97.740349
  },
  {
    "state": "UTAH",
    "city": "Salt Lake City",
    "latitude": 40.777477,
    "longitude": -111.888237
  },
  {
    "state": "VERMONT",
    "city": "Montpelier",
    "latitude": 44.262436,
    "longitude": -72.580536
  },
  {
    "state": "VIRGINIA",
    "city": "Richmond",
    "latitude": 37.538857,
    "longitude": -77.43364
  },
  {
    "state": "WASHINGTON",
    "city": "Olympia",
    "latitude": 47.035805,
    "longitude": -122.905014
  },
  {
    "state": "WEST VIRGINIA",
    "city": "Charleston",
    "latitude": 38.336246,
    "longitude": -81.612328
  },
  {
    "state": "WISCONSIN",
    "city": "Madison",
    "latitude": 43.074684,
    "longitude": -89.384445
  },
  {
    "state": "WYOMING",
    "city": "Cheyenne",
    "latitude": 41.140259,
    "longitude": -104.820236
  }
]
